<?xml version="1.0" encoding="UTF-8"?>
<beans xmlns="http://www.springframework.org/schema/beans"
	xmlns:xsi="http://www.w3.org/2001/XMLSchema-instance"
	xmlns:p="http://www.springframework.org/schema/p"
	xsi:schemaLocation="http://www.springframework.org/schema/beans http://www.springframework.org/schema/beans/spring-beans.xsd">


	<!-- Repository -->	
	<bean id = "jspMenuDAO" class="com.jsp.dao.MenuDAOImpl" />	
	<bean id = "jspNoticeDAO" class="com.jsp.dao.NoticeDAOImpl" />
	<bean id = "jspBoardDAO" class="com.jsp.dao.BoardDAOImpl" />
	<bean id = "jspReplyDAO" class="com.jsp.dao.ReplyDAOImpl" />
	<bean id = "jspPdsDAO" class="com.jsp.dao.PdsDAOImpl" />
	<bean id = "jspAttachDAO" class="com.jsp.dao.AttachDAOImpl" />
	
	<bean id="memberDAO" class="kr.or.ddit.dao.MemberDAOImpl" 
		p:sqlSession-ref="sqlSession"
		/>
	<bean id="menuDAO" class="kr.or.ddit.dao.MenuDAOImpl"
		p:menuDAO-ref="jspMenuDAO"
		p:session-ref="sqlSession"			
	/>
	<bean id="noticeDAO" class="kr.or.ddit.dao.NoticeDAOImpl"
		p:noticeDAO-ref="jspNoticeDAO"
		p:session-ref="sqlSession"	
	/>
	<bean id="boardDAO" class="kr.or.ddit.dao.BoardDAOImpl"
		p:boardDAO-ref="jspBoardDAO"
		p:session-ref="sqlSession"	
	/>
	<bean id="replyDAO" class="kr.or.ddit.dao.ReplyDAOImpl"
		p:replyDAO-ref="jspReplyDAO"
		p:session-ref="sqlSession"	
	/>
	 <bean id="pdsDAO" class="kr.or.ddit.dao.PdsDAOImpl"
		p:pdsDAO-ref="jspPdsDAO"
		p:session-ref="sqlSession"	
	/>
	<bean id="attachDAO" class="kr.or.ddit.dao.AttachDAOImpl"
		p:attachDAO-ref="jspAttachDAO"
		p:session-ref="sqlSession"	
	/>
	
	
	
	<!-- Service -->
	<bean id="memberService" class="com.jsp.service.MemberServiceImpl"
		p:memberDAO-ref="memberDAO"
	/>
	<bean id="menuService" class="kr.or.ddit.service.MenuServiceImpl" 
		p:menuDAO-ref="menuDAO"
	/>
	<bean id="noticeService" class="kr.or.ddit.service.NoticeServiceImpl" 
		p:noticeDAO-ref="noticeDAO"
	/>
	<bean id="boardService" class="kr.or.ddit.service.BoardServiceImpl"		
		p:boardDAO-ref="boardDAO"
		p:replyDAO-ref="replyDAO"
	/>
	<bean id="pdsService" class="kr.or.ddit.service.PdsServiceImpl"
		p:pdsDAO-ref="pdsDAO"
		p:attachDAO-ref="attachDAO"
	/>
	<bean id="replyService" class="kr.or.ddit.service.ReplyServiceImpl"	
		p:replyDAO-ref="replyDAO"		
	/>
	     

</beans>
